MANIFEST.in
README.txt
setup.cfg
setup.py
docs/HISTORY.txt
docs/INSTALL.txt
docs/LICENSE.GPL
docs/LICENSE.txt
sc/__init__.py
sc.paster.theme.egg-info/PKG-INFO
sc.paster.theme.egg-info/SOURCES.txt
sc.paster.theme.egg-info/dependency_links.txt
sc.paster.theme.egg-info/entry_points.txt
sc.paster.theme.egg-info/namespace_packages.txt
sc.paster.theme.egg-info/not-zip-safe
sc.paster.theme.egg-info/requires.txt
sc.paster.theme.egg-info/top_level.txt
sc/paster/__init__.py
sc/paster/theme/__init__.py
sc/paster/theme/portal_theme.py
sc/paster/theme/docs/sc_plone_app.txt
sc/paster/theme/templates/portal_theme/MANIFEST.in_tmpl
sc/paster/theme/templates/portal_theme/setup.cfg
sc/paster/theme/templates/portal_theme/setup.py_tmpl
sc/paster/theme/templates/portal_theme/+namespace_package+/__init__.py
sc/paster/theme/templates/portal_theme/+namespace_package+/+namespace_package2+/__init__.py
sc/paster/theme/templates/portal_theme/+namespace_package+/+namespace_package2+/+package+/README.txt_tmpl
sc/paster/theme/templates/portal_theme/+namespace_package+/+namespace_package2+/+package+/__init__.py_tmpl
sc/paster/theme/templates/portal_theme/+namespace_package+/+namespace_package2+/+package+/config.py_tmpl
sc/paster/theme/templates/portal_theme/+namespace_package+/+namespace_package2+/+package+/configure.zcml_tmpl
sc/paster/theme/templates/portal_theme/+namespace_package+/+namespace_package2+/+package+/skins.zcml_tmpl
sc/paster/theme/templates/portal_theme/+namespace_package+/+namespace_package2+/+package+/tests.py_tmpl
sc/paster/theme/templates/portal_theme/+namespace_package+/+namespace_package2+/+package+/version.txt_tmpl
sc/paster/theme/templates/portal_theme/+namespace_package+/+namespace_package2+/+package+/browser/__init__.py
sc/paster/theme/templates/portal_theme/+namespace_package+/+namespace_package2+/+package+/browser/configure.zcml_tmpl
sc/paster/theme/templates/portal_theme/+namespace_package+/+namespace_package2+/+package+/browser/interfaces.py_tmpl
sc/paster/theme/templates/portal_theme/+namespace_package+/+namespace_package2+/+package+/browser/viewlets.py_tmpl
sc/paster/theme/templates/portal_theme/+namespace_package+/+namespace_package2+/+package+/browser/images/README.txt
