Metadata-Version: 1.0
Name: sc.paster.theme
Version: 0.9
Summary: Produto de tema para o portal Plone (skin).
Home-page: http://www.simplesconsultoria.com.br/
Author: Erico Andrei
Author-email: erico@simplesconsultoria.com.br
License: GPL
Keywords: web zope plone development simples_consultoria
Platform: UNKNOWN
Classifier: Programming Language :: Python
Classifier: Topic :: Software Development :: Libraries :: Python Modules
